LICENSE
MANIFEST.in
README.md
setup.py
pystem/FftCorr.cpp
pystem/FftCorr.h
pystem/__init__.py
pystem/_preselectedtranslations.c
pystem/_stemdescriptor.c
pystem/calculate_descriptor.c
pystem/calculate_descriptor.h
pystem/colorcode.py
pystem/preselected_translations.c
pystem/preselected_translations.h
pystem/preselected_translations.py
pystem/stemclustering.py
pystem/stemdescriptor.py
pystem/stemdescriptor2.cpp
pystem/stempower_spectrum.py
pystem/stemreflection_symmetry_descriptors.py
pystem/stemrotational_symmetry_descriptors.py
pystem/stemsegmentation.py
pystem/stemvertical_horizontal_reflection_symmetry_descriptors.py
pystem/util.py
pystem.egg-info/PKG-INFO
pystem.egg-info/SOURCES.txt
pystem.egg-info/dependency_links.txt
pystem.egg-info/requires.txt
pystem.egg-info/top_level.txt