Metadata-Version: 2.1
Name: pystem
Version: 0.0.26
Summary: A python module for segmentation of STEM images
Home-page: https://github.com/NingWang1990/pySTEM
Author: Ning Wang
Author-email: nwang@mpie.de
Maintainer: Ning Wang
Maintainer-email: nwang@mpie.de
License: GNU GPLv3
Platform: UNKNOWN
Classifier: Intended Audience :: Developers
Classifier: License :: OSI Approved :: GNU General Public License v3 (GPLv3)
Classifier: Operating System :: POSIX :: Linux
Classifier: Programming Language :: Python :: 3
Classifier: Topic :: Security :: Cryptography
Classifier: Topic :: Software Development :: Libraries :: Python Modules
